raven_formats/__init__.py
raven_formats/adpcm.py
raven_formats/fb.py
raven_formats/xmlb.py
raven_formats/zsnd.py
raven_formats/data/__init__.py
raven_formats/data/zsnd_hashes.json
raven_formats-1.8.dist-info/LICENSE.md
raven_formats-1.8.dist-info/METADATA
raven_formats-1.8.dist-info/WHEEL
raven_formats-1.8.dist-info/entry_points.txt
raven_formats-1.8.dist-info/top_level.txt
raven_formats-1.8.dist-info/RECORD
