Metadata-Version: 2.1
Name: raven-formats
Version: 1.8
Summary: Tools to work with formats used by Raven Software in MUA/XML2 games
Home-page: https://github.com/nikita488/raven-formats
Author: nikita488
Project-URL: Bug Tracker, https://github.com/nikita488/raven-formats/issues
Classifier: Development Status :: 5 - Production/Stable
Classifier: Environment :: Console
Classifier: Intended Audience :: Developers
Classifier: License :: OSI Approved :: MIT License
Classifier: Natural Language :: English
Classifier: Operating System :: OS Independent
Classifier: Programming Language :: Python :: 3
Classifier: Programming Language :: Python :: 3.8
Classifier: Programming Language :: Python :: 3.9
Classifier: Programming Language :: Python :: 3.10
Classifier: Programming Language :: Python :: 3.12
Classifier: Programming Language :: Python :: 3 :: Only
Classifier: Topic :: Utilities
Requires-Python: >=3.9
License-File: LICENSE.md
